sonnia/__init__.py
sonnia/classifiers.py
sonnia/compare_repertoires.py
sonnia/evaluate.py
sonnia/generate.py
sonnia/infer.py
sonnia/plotting.py
sonnia/processing.py
sonnia/sonia.py
sonnia/sonia_dataset.py
sonnia/sonia_paired.py
sonnia/sonnia.py
sonnia/sonnia_paired.py
sonnia/utils.py
sonnia/default_models/human_B_heavy/J_gene_CDR3_anchors.csv
sonnia/default_models/human_B_heavy/V_gene_CDR3_anchors.csv
sonnia/default_models/human_B_heavy/features.tsv
sonnia/default_models/human_B_heavy/log.txt
sonnia/default_models/human_B_heavy/model_marginals.txt
sonnia/default_models/human_B_heavy/model_params.txt
sonnia/default_models/human_B_heavy/.ipynb_checkpoints/V_gene_CDR3_anchors-checkpoint.csv
sonnia/default_models/human_B_heavy/.ipynb_checkpoints/model_params-checkpoint.txt
sonnia/default_models/human_B_heavy_kappa/features.tsv
sonnia/default_models/human_B_heavy_kappa/log.txt
sonnia/default_models/human_B_heavy_kappa/heavy_chain/J_gene_CDR3_anchors.csv
sonnia/default_models/human_B_heavy_kappa/heavy_chain/V_gene_CDR3_anchors.csv
sonnia/default_models/human_B_heavy_kappa/heavy_chain/model_marginals.txt
sonnia/default_models/human_B_heavy_kappa/heavy_chain/model_params.txt
sonnia/default_models/human_B_heavy_kappa/light_chain/J_gene_CDR3_anchors.csv
sonnia/default_models/human_B_heavy_kappa/light_chain/V_gene_CDR3_anchors.csv
sonnia/default_models/human_B_heavy_kappa/light_chain/model_marginals.txt
sonnia/default_models/human_B_heavy_kappa/light_chain/model_params.txt
sonnia/default_models/human_B_heavy_lambda/features.tsv
sonnia/default_models/human_B_heavy_lambda/log.txt
sonnia/default_models/human_B_heavy_lambda/heavy_chain/J_gene_CDR3_anchors.csv
sonnia/default_models/human_B_heavy_lambda/heavy_chain/V_gene_CDR3_anchors.csv
sonnia/default_models/human_B_heavy_lambda/heavy_chain/model_marginals.txt
sonnia/default_models/human_B_heavy_lambda/heavy_chain/model_params.txt
sonnia/default_models/human_B_heavy_lambda/light_chain/J_gene_CDR3_anchors.csv
sonnia-0.3.1.dist-info/LICENSE
sonnia-0.3.1.dist-info/METADATA
sonnia-0.3.1.dist-info/WHEEL
sonnia-0.3.1.dist-info/entry_points.txt
sonnia-0.3.1.dist-info/top_level.txt
sonnia-0.3.1.dist-info/RECORD
