Metadata-Version: 2.1
Name: sonnia
Version: 0.3.1
Summary: SoNNia is a Python 3 software developed to infer selection pressures on features of amino acid CDR3 sequences. SoNNia takes as input TCR CDR3 amino acid sequences with  V and J genes. Its output is sequence-level selection factors which indicate how more or less represented this sequence would be in the selected pool as compared to the pre-selected pool. These in turn could be used to calculate the probability of observing any sequence after selection and sample from the selected repert
Author-email: Giulio Isacchini <giulioisac@gmail.com>
Maintainer-email: Giulio Isacchini <giulioisac@gmail.com>
License: GNU GENERAL PUBLIC LICENSE
Project-URL: Homepage, https://github.com/statbiophys/soNNia
Project-URL: Documentation, https://sonnia.readthedocs.io/en/latest/index.html
Classifier: Development Status :: 3 - Alpha
Classifier: Intended Audience :: Developers
Classifier: Intended Audience :: Healthcare Industry
Classifier: Intended Audience :: Science/Research
Classifier: Topic :: Scientific/Engineering :: Bio-Informatics
Classifier: Topic :: Scientific/Engineering :: Physics
Classifier: Topic :: Scientific/Engineering :: Medical Science Apps.
Classifier: License :: OSI Approved :: GNU General Public License v3 (GPLv3)
Classifier: Natural Language :: English
Classifier: Programming Language :: Python :: 3.9
Classifier: Programming Language :: Python :: 3.10
Classifier: Programming Language :: Python :: 3.11
Classifier: Programming Language :: Python :: 3.12
Requires-Python: >=3.9
License-File: LICENSE
Requires-Dist: keras >=3
Requires-Dist: matplotlib
Requires-Dist: olga >=1.1.3
Requires-Dist: numpy
Requires-Dist: pandas
Requires-Dist: seaborn
Requires-Dist: scikit-learn
Requires-Dist: scipy >=1.10
Requires-Dist: tensorflow >=2.16
Requires-Dist: tqdm
